triton_patched-2.1.1.dist-info/METADATA
triton_patched-2.1.1.dist-info/top_level.txt
triton_patched-2.1.1.dist-info/RECORD
triton_patched-2.1.1.dist-info/WHEEL
triton/testing.py
triton/__init__.py
triton/common/backend.py
triton/common/__init__.py
triton/common/build.py
triton/interpreter/tl_lang.py
triton/interpreter/interpreter.py
triton/interpreter/__init__.py
triton/interpreter/core.py
triton/interpreter/memory_map.py
triton/interpreter/torch_wrapper.py
triton/_C/libtriton.so
triton/compiler/errors.py
triton/compiler/compiler.py
triton/compiler/__init__.py
triton/compiler/make_launcher.py
triton/compiler/code_generator.py
triton/tools/compile.h
triton/tools/compile.c
triton/tools/link.py
triton/tools/__init__.py
triton/tools/compile.py
triton/tools/build_extern.py
triton/tools/disasm.py
triton/ops/flash_attention.py
triton/ops/matmul_perf_model.py
triton/ops/cross_entropy.py
triton/ops/matmul.py
triton/ops/__init__.py
triton/ops/blocksparse/softmax.py
triton/ops/blocksparse/matmul.py
triton/ops/blocksparse/__init__.py
triton/language/random.py
triton/language/standard.py
triton/language/math.py
triton/language/__init__.py
triton/language/core.py
triton/language/semantic.py
triton/language/extra/cuda.py
triton/language/extra/cuda.bc
triton/language/extra/__init__.py
triton/runtime/errors.py
triton/runtime/autotuner.py
triton/runtime/__init__.py
triton/runtime/driver.py
triton/runtime/cache.py
triton/runtime/jit.py
triton/runtime/backends/cuda.c
triton/runtime/backends/hip.c
triton/third_party/cuda/lib/libdevice.10.bc
triton/third_party/cuda/include/cuda.h
triton/third_party/cuda/bin/ptxas
